<?xml version="1.0" encoding="UTF-8" standalone="yes"?>
<root>
  <latitude>40.722767</latitude>
  <longitude>-73.91525</longitude>
  <generationtime_ms>0.29408931732177734</generationtime_ms>
  <utc_offset_seconds>-18000</utc_offset_seconds>
  <timezone>America/New_York</timezone>
  <timezone_abbreviation>EST</timezone_abbreviation>
  <elevation>38</elevation>
  <daily_units>
    <time>iso8601</time>
    <weather_code>wmo code</weather_code>
    <temperature_2m_max>°C</temperature_2m_max>
    <apparent_temperature_max>°C</apparent_temperature_max>
    <precipitation_probability_max>%</precipitation_probability_max>
    <wind_speed_10m_max>km/h</wind_speed_10m_max>
    <wind_direction_10m_dominant>°</wind_direction_10m_dominant>
  </daily_units>
  <daily>
    <time>2024-02-02</time>
    <time>2024-02-03</time>
    <time>2024-02-04</time>
    <time>2024-02-05</time>
    <time>2024-02-06</time>
    <time>2024-02-07</time>
    <time>2024-02-08</time>
    <weather_code>63</weather_code>
    <weather_code>3</weather_code>
    <weather_code>0</weather_code>
    <weather_code>0</weather_code>
    <weather_code>0</weather_code>
    <weather_code>3</weather_code>
    <weather_code>3</weather_code>
    <temperature_2m_max>6.3</temperature_2m_max>
    <temperature_2m_max>2.6</temperature_2m_max>
    <temperature_2m_max>6.5</temperature_2m_max>
    <temperature_2m_max>4.8</temperature_2m_max>
    <temperature_2m_max>4</temperature_2m_max>
    <temperature_2m_max>5.1</temperature_2m_max>
    <temperature_2m_max>10.7</temperature_2m_max>
    <apparent_temperature_max>3.6</apparent_temperature_max>
    <apparent_temperature_max>-2.6</apparent_temperature_max>
    <apparent_temperature_max>2.4</apparent_temperature_max>
    <apparent_temperature_max>-0.9</apparent_temperature_max>
    <apparent_temperature_max>-1.1</apparent_temperature_max>
    <apparent_temperature_max>1</apparent_temperature_max>
    <apparent_temperature_max>6.4</apparent_temperature_max>
    <precipitation_probability_max>97</precipitation_probability_max>
    <precipitation_probability_max>0</precipitation_probability_max>
    <precipitation_probability_max>0</precipitation_probability_max>
    <precipitation_probability_max>0</precipitation_probability_max>
    <precipitation_probability_max>0</precipitation_probability_max>
    <precipitation_probability_max>0</precipitation_probability_max>
    <precipitation_probability_max>0</precipitation_probability_max>
    <wind_speed_10m_max>18.6</wind_speed_10m_max>
    <wind_speed_10m_max>20.1</wind_speed_10m_max>
    <wind_speed_10m_max>12.6</wind_speed_10m_max>
    <wind_speed_10m_max>19.1</wind_speed_10m_max>
    <wind_speed_10m_max>14.5</wind_speed_10m_max>
    <wind_speed_10m_max>9.7</wind_speed_10m_max>
    <wind_speed_10m_max>11.5</wind_speed_10m_max>
    <wind_direction_10m_dominant>336</wind_direction_10m_dominant>
    <wind_direction_10m_dominant>347</wind_direction_10m_dominant>
    <wind_direction_10m_dominant>355</wind_direction_10m_dominant>
    <wind_direction_10m_dominant>12</wind_direction_10m_dominant>
    <wind_direction_10m_dominant>11</wind_direction_10m_dominant>
    <wind_direction_10m_dominant>339</wind_direction_10m_dominant>
    <wind_direction_10m_dominant>250</wind_direction_10m_dominant>
  </daily>
</root>